{"notify":{"id":531,"type":"debtStatus","version":1,"time":"2020-12-08T17:25:49+00:00","merchant":"el-mercadi369","app":"web","env":"test"},"debt":{"docId":"15fcfb6ef930fd","label":"Factura de ventas: 001-002-15fcfb6ef930fd (Jugo de arroz)","slug":"15fcfb6ef930fd","payUrl":"https:\/\/staging.adamspay.com\/pay\/el-mercadi369\/debt\/15fcfb6ef930fd","amount":{"currency":"PYG","value":"25000.000000","paid":"25000.000000"},"exchangeMode":null,"target":{"type":null,"number":null,"label":null},"description":null,"validPeriod":{"start":"2020-12-08T17:25:03+00:00","end":"2020-12-10T17:25:03+00:00"},"payStatus":{"status":"paid","code":null,"time":"2020-12-08T17:25:49+00:00","text":null},"statusHash":"0c211fdc21b83d4dd9d79704374d7a2b","attr":null,"notifyUrl":null,"uiTheme":null,"objId":"10996","objStatus":{"status":"success","code":null,"time":"2020-12-08T17:25:49+00:00","text":null},"created":"2020-12-08T17:25:03+00:00","updated":"2020-12-08T17:25:49+00:00","refs":{"txList":[{"txId":"4408007000873","type":"debtDocPay","objStatus":{"status":"success","code":null,"time":"2020-12-08T17:25:49+00:00","text":"This is a simulated response"},"provider":"adams","method":"simulator","material":"generic","correlationId":"2b855e5e11-11032","providerStatus":{"time":"2020-12-08T17:25:49+00:00","resultCode":"01","authCode":"57813","message":"This is a simulated response"},"origAmount":{"currency":"PYG","value":"25000.000000"},"realAmount":{"currency":"PYG","value":"25000.000000"},"exchangeRate":null,"initiator":"ui.user","created":"2020-12-08T17:25:49+00:00","updated":"2020-12-08T17:25:49+00:00","expires":"2020-12-08T20:25:49+00:00","verified":null,"finalized":"2020-12-08T17:25:49+00:00","objId":"11032"}],"attachments":[]},"meta":{"merchantObjId":"1059","appObjId":"120","firstTxObjId":"11032","lastTxObjId":"11032"}}}